pdfextbook/__init__.py
pdfextbook/pdfextbook.py
pdfextbook-0.0.3.dist-info/LICENSE
pdfextbook-0.0.3.dist-info/METADATA
pdfextbook-0.0.3.dist-info/WHEEL
pdfextbook-0.0.3.dist-info/entry_points.txt
pdfextbook-0.0.3.dist-info/RECORD
