Metadata-Version: 2.1
Name: pdfextbook
Version: 0.0.3
Summary: Extract pages from PDF on bookmark boundaries. 
Home-page: https://github.com/raffaem/pdfextbook
License: MIT
Author: Raffaele Mancuso
Author-email: raffaelemancuso532@gmail.com
Requires-Python: >=3.12,<4.0
Classifier: License :: OSI Approved :: MIT License
Classifier: Programming Language :: Python :: 3
Classifier: Programming Language :: Python :: 3.12
Requires-Dist: numpy (>=2.1.2,<3.0.0)
